Workbook

Sheet Media Plan
A1: eSprinto G1 - Paid Media Plan - Teaser Phase
A2: 22 September - 12 October 2026 | Platform: Meta (Facebook + Instagram) only | Scenario shown: Moderate (recommended base case) - all figures below are live formulas linked to 'Multiple Projections'
A4: Campaign Summary
A5: Campaign / Ad Set | B5: Duration | C5: Objective | D5: Total Budget | E5: Audience Size | F5: Impressions | G5: Reach | H5: Leads / Follows
A6: Campaign 1 - Awareness (Post Boosting) | B6: 22 Sept - 12 Oct (21 days) | C6: Brand Awareness + Reach | D6: ='Multiple Projections'!D7 | E6: ='Multiple Projections'!I7 | F6: ='Multiple Projections'!F7 | G6: ='Multiple Projections'!H7 | H6: ='Multiple Projections'!R7
A7: Campaign 2 / Ad Set 2A - Broad Audience (Prospecting) | B7: 3 Oct - 12 Oct (10 days) | C7: Lead Gen - Pre-Booking / Test Ride Interest | D7: ='Multiple Projections'!B13 | E7: ='Multiple Projections'!G13 | F7: ='Multiple Projections'!D13 | G7: ='Multiple Projections'!F13 | H7: ='Multiple Projections'!P13
A8: Campaign 2 / Ad Set 2B - Warm Pool (Remarketing) | B8: 3 Oct - 12 Oct (10 days) | C8: Lead Gen - Pre-Booking / Test Ride Interest | D8: ='Multiple Projections'!H19 | E8: ='Multiple Projections'!B19 | F8: ='Multiple Projections'!D19 | G8: ='Multiple Projections'!E19 | H8: ='Multiple Projections'!P19
A9: Campaign 2 Total (2A + 2B) | B9: 3 Oct - 12 Oct (10 days) | C9: - | D9: ='Multiple Projections'!H25 | E9: - | F9: ='Multiple Projections'!D13+'Multiple Projections'!D19 | G9: - | H9: ='Multiple Projections'!I25
A10: TEASER PHASE TOTAL | B10: 22 Sept - 12 Oct | C10: - | D10: ='Multiple Projections'!J25 | E10: - | F10: ='Multiple Projections'!F7+'Multiple Projections'!D13+'Multiple Projections'!D19 | G10: - | H10: ='Multiple Projections'!K25
A12: Scope Notes
A13: Platforms in this phase | B13: Meta only. Google Ads, ShareChat and ChatGPT Ads are not part of Teaser - they begin at Launch (13 Oct 2026).
A14: Posts boosted (Campaign 1) | B14: 5-10 posts (changed from an earlier 26-post plan). This file uses 7 posts as the Moderate/base case; see 'Multiple Projections' for the 5-post and 10-post scenarios.
A15: Campaign 2 structure | B15: Pre-Booking runs as one campaign with two ad sets: 2A targets the broad/cold Facebook audience (same targeting as Campaign 1) as the primary volume driver, and 2B retargets the Campaign 1 warm pool as a smaller remarketing layer.
A16: Influencers | B16: Excluded from this media plan for now - to be scoped and confirmed as a separate workstream.
A17: Test ride / pre-booking destination | B17: Website or Meta Instant Form - to be A/B tested once live. Not a blocker for this plan; both paths are budgeted identically.
A18: Why no product/marketplace CTA in Teaser | B18: eSprinto cannot list or sell the scooter anywhere until the 13 Oct launch. Campaign 1 asks only for attention (watch/follow); Campaign 2 asks only for pre-registration - never for purchase.
A19: Full scenario breakdown + full funnel | B19: See 'Multiple Projections' for Conservative / Moderate / Aggressive numbers, and 'Detailed Media Plan' for the complete Impressions -> CTR -> Clicks -> CVR -> Leads breakdown per campaign / ad set.
A20: Editing this plan | B20: Every number on this sheet is a formula pulling from 'Multiple Projections'. To test a different number with the client, edit the input cells (white, unformatted-as-formula) in 'Multiple Projections' - everything here updates automatically.

Sheet Audience Targeting
A1: eSprinto G1 - Audience Targeting - Teaser Phase
A3: Campaign 1 - Cold Audience (C1)
A4: Target group | B4: EV-aware adults actively interested in electric two-wheelers and sustainable transport
A5: Age | B5: 22 - 50
A6: Gender | B6: All
A7: Locations (28 cities) | B7: Guntur, Vijayawada, Hyderabad, Nizamabad, Bangalore, Mysuru, Mangalore, Chennai, Coimbatore, Kochi, Calicut, Thiruvananthapuram, Ahmedabad, Surat, Vadodara, Mumbai, Pune, Nagpur, Nashik, Aurangabad, Panaji (Goa), Indore, Bhopal, Ghaziabad, Noida, Jaipur, Jodhpur, Udaipur
A8: Interests - Additional interests | B8: Electric motorcycles and scooters, Electric bicycle, Hybrid electric vehicle, Motorcycle accessories, Sustainable transport
A9: Interests - Hobbies & activities > Vehicles | B9: Electric vehicle, Hybrids, Motorcycles, Scooters
A10: Audience size (Meta estimate) | B10: 2,00,00,000 - 3,00,00,000 (Awareness objective, 28-city footprint)
A11: Placement | B11: Advantage+ placements (Instagram Reels prioritised for awareness)
A12: Optimisation goal | B12: Reach - maximise unique people reached, not clicks or leads
A13: Exclusion | B13: Custom audience: all Meta page engagers BEFORE 22 Sept 2026 (excludes B2B dealership-recruitment audience contamination)
A15: Campaign 2 / Ad Set 2A - Broad Audience (Prospecting)
A16: Target group | B16: Same targeting as Campaign 1 - EV-aware adults interested in electric two-wheelers and sustainable transport. Not warm-pool-dependent, so this ad set can run at full scale from day one of Campaign 2 regardless of how the Campaign 1 warm pool is tracking.
A17: Age / Gender / Locations | B17: 22 - 50, all genders, same 28 cities as Campaign 1
A18: Interests | B18: Same interest stack as Campaign 1 (see above)
A19: Audience size (Meta estimate) | B19: 2,00,00,000 - 3,00,00,000 - same pool as Campaign 1, but this ad set optimises for Leads, not Reach, so Meta's auction and CPM behave differently even on identical targeting
A20: Placement | B20: Advantage+ placements
A21: Optimisation goal | B21: Leads (Meta Lead Form completion) or link clicks to website - destination TBD
A22: Exclusion | B22: Same B2B exclusion as Campaign 1: all page engagers BEFORE 22 Sept 2026
A23: CTA | B23: Register Interest / Book a Test Ride - 'eSprinto G1 launches 13 Oct - reserve your spot'
A24: Lead form fields (if Instant Form used) | B24: Name, Phone number, City, 'When are you planning to buy a scooter?'
A25: Why this is now the primary pre-booking driver | B25: Broad audience volume does not depend on Campaign 1's warm-pool build-up, so it is not capped by post count or engagement timing the way pure retargeting is. This is the main lever for pre-booking lead volume.
A27: Campaign 2 / Ad Set 2B - Warm Pool (Remarketing)
A28: Target group | B28: B2C warm audience - people who engaged with eSprinto content after 22 Sept 2026 only. Supplementary to 2A, not the primary volume source.
A29: Custom audience definition | B29: Video viewers (60%+ of any eSprinto reel posted after 22 Sept 2026); post engagers (likes, comments, shares after 22 Sept 2026); profile visitors (Instagram/Facebook, after 22 Sept 2026); website visitors after 22 Sept 2026 if pixel is active
A30: Age / Gender / Locations | B30: Inherited from custom audience (same 28 cities, 22-50, all genders)
A31: Exclusion | B31: All page engagers BEFORE 22 Sept 2026 - same B2B exclusion logic as Campaign 1 and 2A
A32: Placement | B32: Instagram Stories + Reels - high-frequency, short-form retargeting
A33: Optimisation goal | B33: Leads (Meta Lead Form completion) or link clicks to website - destination TBD
A34: CTA | B34: Register Interest / Book a Test Ride - same messaging as 2A, higher-frequency delivery since this is an already-warm audience
A35: Why this audience is small at campaign start | B35: Campaign 2 begins 3 Oct - only 11 days into a 21-day Campaign 1. The warm pool is still building and has not reached its full Teaser-end size yet. Because 2A now carries the primary lead volume, this no longer caps overall Campaign 2 performance the way it would if 2B were run alone - see 'Multiple Projections' for the sizing detail.

Sheet Road Map
A1: eSprinto G1 - Road Map - Teaser Phase
A3: Phase | B3: Campaign / Ad Set | C3: Campaign Objective | D3: Objective (Meta) | E3: Posts | F3: Duration | G3: Destination | H3: CTA
A4: Teaser | B4: Campaign 1 - Awareness | C4: Build cold-audience reach + seed warm pool | D4: Brand Awareness / Reach | E4: 5-10 | F4: 22 Sept - 12 Oct 2026 (21 days) | G4: Post engagement only - no landing page or product listing (nothing to sell yet) | H4: Watch More / Follow
A5: Teaser | B5: Campaign 2 / Ad Set 2A - Broad Audience | C5: Drive primary pre-booking lead volume from the full cold Facebook audience | D5: Lead Generation | E5: N/A (prospecting ad set) | F5: 3 Oct - 12 Oct 2026 (10 days) | G5: Website or Meta Instant Form - to be A/B tested (destination TBD) | H5: Register Interest / Book a Test Ride
A6: Teaser | B6: Campaign 2 / Ad Set 2B - Warm Pool | C6: Convert already-engaged Campaign 1 audience as a supplementary remarketing layer | D6: Lead Generation | E6: N/A (remarketing ad set) | F6: 3 Oct - 12 Oct 2026 (10 days) | G6: Website or Meta Instant Form - to be A/B tested (destination TBD) | H6: Register Interest / Book a Test Ride
A8: Phase Boundary Note
A9: Teaser ends 12 Oct | B9: Launch begins 13 Oct 2026 with Google Ads, ShareChat and ChatGPT Ads added alongside Meta. Warm pool built here carries directly into Launch-phase Meta remarketing.

Sheet Detailed Media Plan
A1: eSprinto G1 - Detailed Media Plan - Teaser Phase (Moderate scenario)
A2: Every column is filled with a real number - engagement, click and lead metrics are shown for every campaign / ad set, even where they are not the primary optimisation objective. Conservative and Aggressive scenarios are in 'Multiple Projections'. All cells here are formulas linked to that sheet's Moderate row.
A4: Campaign / Ad Set | B4: Objective | C4: KPI | D4: Daily Spend | E4: Total Spend | F4: Audience Size | G4: Reach | H4: % Audience Reached | I4: Frequency | J4: Impressions | K4: CPM | L4: Engagement Rate | M4: Engagement | N4: CPE | O4: CTR | P4: Clicks | Q4: CPC | R4: CVR | S4: Leads / Follows | T4: CPL / Cost per Follow
A5: Campaign 1 - Awareness | B5: Brand Awareness + Reach | C5: Reach / Impressions / Follows | D5: ='Multiple Projections'!D7/21 | E5: ='Multiple Projections'!D7 | F5: ='Multiple Projections'!I7 | G5: ='Multiple Projections'!H7 | H5: ='Multiple Projections'!J7 | I5: ='Multiple Projections'!G7 | J5: ='Multiple Projections'!F7 | K5: ='Multiple Projections'!E7 | L5: ='Multiple Projections'!K7 | M5: ='Multiple Projections'!L7 | N5: ='Multiple Projections'!M7 | O5: ='Multiple Projections'!N7 | P5: ='Multiple Projections'!O7 | Q5: ='Multiple Projections'!P7 | R5: ='Multiple Projections'!Q7 | S5: ='Multiple Projections'!R7 | T5: ='Multiple Projections'!S7
A6: Ad Set 2A - Broad Audience | B6: Lead Generation | C6: Leads / CPL | D6: ='Multiple Projections'!B13/10 | E6: ='Multiple Projections'!B13 | F6: ='Multiple Projections'!G13 | G6: ='Multiple Projections'!F13 | H6: ='Multiple Projections'!H13 | I6: ='Multiple Projections'!E13 | J6: ='Multiple Projections'!D13 | K6: ='Multiple Projections'!C13 | L6: ='Multiple Projections'!I13 | M6: ='Multiple Projections'!J13 | N6: ='Multiple Projections'!K13 | O6: ='Multiple Projections'!L13 | P6: ='Multiple Projections'!M13 | Q6: ='Multiple Projections'!N13 | R6: ='Multiple Projections'!O13 | S6: ='Multiple Projections'!P13 | T6: ='Multiple Projections'!Q13
A7: Ad Set 2B - Warm Pool | B7: Lead Generation | C7: Leads / CPL | D7: ='Multiple Projections'!H19/10 | E7: ='Multiple Projections'!H19 | F7: ='Multiple Projections'!B19 | G7: ='Multiple Projections'!E19 | H7: ='Multiple Projections'!F19 | I7: ='Multiple Projections'!C19 | J7: ='Multiple Projections'!D19 | K7: ='Multiple Projections'!G19 | L7: ='Multiple Projections'!I19 | M7: ='Multiple Projections'!J19 | N7: ='Multiple Projections'!K19 | O7: ='Multiple Projections'!L19 | P7: ='Multiple Projections'!M19 | Q7: ='Multiple Projections'!N19 | R7: ='Multiple Projections'!O19 | S7: ='Multiple Projections'!P19 | T7: ='Multiple Projections'!Q19
A8: Campaign 2 Total (2A + 2B) | B8: Lead Generation | C8: Leads / CPL (blended) | D8: ='Multiple Projections'!H25/10 | E8: ='Multiple Projections'!H25 | F8: - | G8: - | H8: - | I8: - | J8: ='Multiple Projections'!D13+'Multiple Projections'!D19 | K8: - | L8: - | M8: - | N8: - | O8: - | P8: - | Q8: - | R8: - | S8: ='Multiple Projections'!I25 | T8: ='Multiple Projections'!H25/'Multiple Projections'!I25
A10: Formulas Used (documented in 'Multiple Projections'; this sheet only links to it)
A11: - Impressions = Total Spend / CPM x 1,000 | Reach = Impressions / Frequency | % Audience Reached = Reach / Audience Size
A12: - Engagement = Impressions x Engagement Rate | CPE = Total Spend / Engagement
A13: - Clicks = Impressions x CTR | CPC = Total Spend / Clicks
A14: - Leads (or Follows, Campaign 1) = Clicks x CVR | CPL (or Cost per Follow) = Total Spend / Leads
A15: - Warm pool @ 3 Oct (Campaign 1) = Engagement x time-elapsed fraction (11 of 21 Teaser days)
A16: - Ad Set 2B Audience = Campaign 1's Warm Pool @ 3 Oct (same-sheet cell reference) - so posting more/fewer posts in Campaign 1 changes 2B's audience, impressions and budget automatically
A17: - Ad Set 2A budget is a scenario input (audience is large enough that budget, not audience size, is the constraint); Ad Set 2B budget is derived from Audience x Frequency / 1,000 x CPM (audience is the constraint here)

Sheet Multiple Projections
A1: eSprinto G1 - Multiple Projections - Teaser Phase
A2: Every shaded input (Budget/Posts, CPM, Frequency, CTR, CVR, Engagement Rate) is a typed assumption - every other cell is a live formula. Change an input and its row recalculates.
A4: Campaign 1 - Awareness (22 Sept - 12 Oct, 21 days)
A5: Scenario | B5: Posts | C5: Budget /Post | D5: Total Budget | E5: CPM | F5: Impressions | G5: Frequency | H5: Reach | I5: Audience Size | J5: % Audience Reached | K5: Engagement Rate | L5: Engagement / Warm Pool (12 Oct) | M5: CPE | N5: CTR | O5: Clicks | P5: CPC | Q5: CVR (click->follow) | R5: Follows / Profile Visits | S5: Cost per Follow | T5: Time Frac. elapsed @ 3 Oct | U5: Warm Pool @ 3 Oct (2B start)
A6: Conservative | B6: 5 | C6: 1000 | D6: =C6*B6 | E6: 80 | F6: =D6/E6*1000 | G6: 2.2 | H6: =F6/G6 | I6: 25000000 | J6: =H6/I6 | K6: 0.05 | L6: =F6*K6 | M6: =D6/L6 | N6: 0.007 | O6: =F6*N6 | P6: =D6/O6 | Q6: 0.08 | R6: =O6*Q6 | S6: =D6/R6 | T6: 0.5238 | U6: =L6*T6
A7: Moderate | B7: 7 | C7: 1250 | D7: =C7*B7 | E7: 80 | F7: =D7/E7*1000 | G7: 2.3 | H7: =F7/G7 | I7: 25000000 | J7: =H7/I7 | K7: 0.075 | L7: =F7*K7 | M7: =D7/L7 | N7: 0.008 | O7: =F7*N7 | P7: =D7/O7 | Q7: 0.09 | R7: =O7*Q7 | S7: =D7/R7 | T7: 0.5238 | U7: =L7*T7
A8: Aggressive | B8: 10 | C8: 1500 | D8: =C8*B8 | E8: 80 | F8: =D8/E8*1000 | G8: 2.5 | H8: =F8/G8 | I8: 25000000 | J8: =H8/I8 | K8: 0.1 | L8: =F8*K8 | M8: =D8/L8 | N8: 0.009 | O8: =F8*N8 | P8: =D8/O8 | Q8: 0.1 | R8: =O8*Q8 | S8: =D8/R8 | T8: 0.5238 | U8: =L8*T8
A10: Campaign 2 / Ad Set 2A - Broad Audience Prospecting (3 Oct - 12 Oct, 10 days)
A11: Scenario | B11: Total Budget | C11: CPM | D11: Impressions | E11: Frequency | F11: Reach | G11: Audience Size | H11: % Audience Reached | I11: Engagement Rate | J11: Engagement | K11: CPE | L11: CTR | M11: Clicks | N11: CPC | O11: CVR (click->lead) | P11: Leads | Q11: CPL
A12: Conservative | B12: 8000 | C12: 120 | D12: =B12/C12*1000 | E12: 2 | F12: =D12/E12 | G12: 25000000 | H12: =F12/G12 | I12: 0.012 | J12: =D12*I12 | K12: =B12/J12 | L12: 0.013 | M12: =D12*L12 | N12: =B12/M12 | O12: 0.021 | P12: =M12*O12 | Q12: =B12/P12
A13: Moderate | B13: 12000 | C13: 120 | D13: =B13/C13*1000 | E13: 2.1 | F13: =D13/E13 | G13: 25000000 | H13: =F13/G13 | I13: 0.014 | J13: =D13*I13 | K13: =B13/J13 | L13: 0.014 | M13: =D13*L13 | N13: =B13/M13 | O13: 0.022 | P13: =M13*O13 | Q13: =B13/P13
A14: Aggressive | B14: 20000 | C14: 120 | D14: =B14/C14*1000 | E14: 2.2 | F14: =D14/E14 | G14: 25000000 | H14: =F14/G14 | I14: 0.016 | J14: =D14*I14 | K14: =B14/J14 | L14: 0.015 | M14: =D14*L14 | N14: =B14/M14 | O14: 0.023 | P14: =M14*O14 | Q14: =B14/P14
A16: Campaign 2 / Ad Set 2B - Warm Pool Remarketing (3 Oct - 12 Oct, 10 days)
A17: Scenario | B17: Audience (Warm Pool @3Oct) | C17: Frequency | D17: Impressions | E17: Reach | F17: % Audience Reached | G17: CPM | H17: Total Budget | I17: Engagement Rate | J17: Engagement | K17: CPE | L17: CTR | M17: Clicks | N17: CPC | O17: CVR (click->lead) | P17: Leads | Q17: CPL
A18: Conservative | B18: =U6 | C18: 3.5 | D18: =B18*C18 | E18: =D18/C18 | F18: =E18/B18 | G18: 200 | H18: =D18/1000*G18 | I18: 0.02 | J18: =D18*I18 | K18: =H18/J18 | L18: 0.035 | M18: =D18*L18 | N18: =H18/M18 | O18: 0.04 | P18: =M18*O18 | Q18: =H18/P18
A19: Moderate | B19: =U7 | C19: 4 | D19: =B19*C19 | E19: =D19/C19 | F19: =E19/B19 | G19: 200 | H19: =D19/1000*G19 | I19: 0.023 | J19: =D19*I19 | K19: =H19/J19 | L19: 0.04 | M19: =D19*L19 | N19: =H19/M19 | O19: 0.05 | P19: =M19*O19 | Q19: =H19/P19
A20: Aggressive | B20: =U8 | C20: 4.5 | D20: =B20*C20 | E20: =D20/C20 | F20: =E20/B20 | G20: 200 | H20: =D20/1000*G20 | I20: 0.026 | J20: =D20*I20 | K20: =H20/J20 | L20: 0.045 | M20: =D20*L20 | N20: =H20/M20 | O20: 0.06 | P20: =M20*O20 | Q20: =H20/P20
A22: Campaign 2 Combined (2A + 2B) and Teaser Phase Total
A23: Scenario | B23: Campaign 1 Budget | C23: Campaign 1 Follows | D23: Ad Set 2A Budget | E23: Ad Set 2A Leads | F23: Ad Set 2B Budget | G23: Ad Set 2B Leads | H23: Campaign 2 Combined Budget | I23: Campaign 2 Combined Leads | J23: Teaser Total Budget | K23: Teaser Total Leads
A24: Conservative | B24: =D6 | C24: =R6 | D24: =B12 | E24: =P12 | F24: =H18 | G24: =P18 | H24: =D24+F24 | I24: =E24+G24 | J24: =B24+H24 | K24: =I24
A25: Moderate | B25: =D7 | C25: =R7 | D25: =B13 | E25: =P13 | F25: =H19 | G25: =P19 | H25: =D25+F25 | I25: =E25+G25 | J25: =B25+H25 | K25: =I25
A26: Aggressive | B26: =D8 | C26: =R8 | D26: =B14 | E26: =P14 | F26: =H20 | G26: =P20 | H26: =D26+F26 | I26: =E26+G26 | J26: =B26+H26 | K26: =I26
A28: Strategic Note - Why Campaign 2 Is Split Into Two Ad Sets
A29: Ad Set 2A (broad audience) carries the primary pre-booking lead volume: it runs on the same ~2.5 crore cold Facebook audience as Campaign 1, so its scale does not depend on how many posts ran or how large the warm pool has grown by 3 Oct. Ad Set 2B (warm pool) is a smaller, supplementary layer that retargets people already engaging with eSprinto content - a warm audience converts at a meaningfully lower cost per lead than cold prospecting (see CPL columns above), but its scale is capped by warm-pool size and timing. Posting more in Campaign 1 (toward 10 posts) still helps 2B's efficiency and reach, but no longer gates the whole campaign's pre-booking volume the way it would if 2B ran alone.
A31: Assumptions to Validate Once Live
A32: CPM, Frequency, Engagement Rate, CTR and CVR inputs (white cells above) are India Meta planning benchmarks for a new EV-scooter brand - not eSprinto account data, since eSprinto's existing Meta history is the B2B dealership campaign, which is not comparable. CTR/CVR are set so cold prospecting (2A) lands at a higher, more realistic cost-per-lead than warm remarketing (2B), reflecting that warm audiences convert more efficiently. Replace any input with actual data once each ad set has 7 days live, and every formula in this sheet - plus the Media Plan and Detailed Media Plan summaries, which pull from these same cells - recalculates automatically.

Sheet Creative Strategy Requirement
A1: eSprinto G1 - Creative Strategy Requirement - Teaser Phase (Pre-Booking)
A2: Top 4 concepts for Campaign 2 / Ad Set 2A + 2B (Pre-Booking, 3-12 Oct). Campaign 1 (Awareness) creative concepts to be added separately once agreed.
A4: Phase | B4: Campaign | C4: Objective | D4: Format | E4: Formula | F4: Hook Style | G4: CTA | H4: Concept Reference | I4: Creative Copy Timeline | J4: Creative Copy Finalisation | K4: Creative Timeline | L4: Final Drafts to be ready by | M4: Client Review Date | N4: Tentative Campaign Launch Date
A5: Teaser | B5: Campaign 2 - Pre-Booking (Ad Set 2A + 2B) | C5: Lead Generation - Pre-Booking / Test Ride Interest | D5: Static / Carousel | E5: Offer callout + low-friction booking amount + urgency line | F5: Value-led / deal-forward - e.g. "Reserve your eSprinto for just Rs.[X] - fully refundable. First [N] bookings get [early-bird perk]." | G5: Reserve Now / Book for Rs.[X] | H5: Pattern seen in TVS iQube cashback ad (Rs.17,300 cashback + Rs.2,100 booking amount) and Ampere Primus cashback ad (Rs.6,000 cash discount, time-boxed) - original eSprinto creative, not reused imagery | I5: 46282 | J5: 46283 | K5: 46287 | L5: 46288 | M5: 46290 | N5: 46298
A6: Teaser | B6: Campaign 2 - Pre-Booking (Ad Set 2A + 2B) | C6: Lead Generation - Pre-Booking / Test Ride Interest | D6: Carousel (city cards) / Static (per-city variant) | E6: City name + "coming to your city" + reserve CTA, run as localised variants across the 28 target cities | F6: Locality-led - e.g. "eSprinto is coming to Jaipur. Be one of the first to ride it - reserve your spot." | G6: Reserve Your Spot in [City] | H6: Pattern seen in Hero Destini 125 "Booking Open @Jamnagar" ad - original eSprinto creative, not reused imagery | I6: 46282 | J6: 46283 | K6: 46288 | L6: 46289 | M6: 46291 | N6: 46298
A7: Teaser | B7: Campaign 2 - Pre-Booking (Ad Set 2A + 2B) | C7: Lead Generation - Pre-Booking / Test Ride Interest | D7: Video (short animated explainer / talking head) | E7: Problem (petrol cost) + Insight (monthly savings math) + CTA | F7: Savings-led / rational - e.g. "You spent Rs.[X] on petrol last month. On eSprinto, that's Rs.[Y]. Reserve your test ride and see the difference." | G7: Calculate Your Savings / Reserve a Test Ride | H7: No direct competitor reference in the reviewed set - built from eSprinto's own validated savings positioning (brief: Rs.2,000-4,200/month savings vs petrol) | I7: 46281 | J7: 46283 | K7: 46292 | L7: 46293 | M7: 46295 | N7: 46298
A8: Teaser | B8: Campaign 2 - Pre-Booking (Ad Set 2A + 2B) | C8: Lead Generation - Pre-Booking / Test Ride Interest | D8: Story / Reel (short-form, 10-15 sec) | E8: Countdown/urgency + scarcity line + CTA - refresh every 2-3 days as date/count changes | F8: Urgency-led - e.g. "13 October. [X] days left to reserve before launch." / "Early-bird slots filling up - [Y] riders already registered." | G8: Reserve Before Launch | H8: No direct reference in the reviewed set - all 10 references were live booking/purchase ads, not pre-launch countdown creative; genuinely new territory for this set | I8: 46284 | J8: 46285 | K8: 46290 | L8: 46291 | M8: 46293 | N8: 46298
A10: Notes
A11: Source of reference patterns | B11: Analysed from 10 competitor/dealer creative references (Honda ADV160, TVS dealer lineups, Honda festive multi-model, Ampere x2, Bajaj Chetak, Hero Destini, TVS iQube) shared via Esprinto-Creative-References.rtf - grouped into 6 territories present in the references (Incentive Trigger, Local Proof, Spec Credibility, Lifestyle Aspiration, Segment Fit, Positioning Claim) plus 4 territories identified as missing/valuable but not used by any reference (The Math That Sells Itself, Real Riders Real Cities, Earning Trust as the New Kid, The Countdown). These 4 rows are the top picks for pre-booking specifically.
A12: Why these 4 and not the others | B12: Spec Credibility and Positioning Claim need a product reveal not available until Launch (13 Oct). Lifestyle Aspiration and Segment Fit build brand relevance but don't drive a specific pre-booking action - better suited to Campaign 1 (Awareness). Trust-building (new-brand credibility) is a longer-arc job than a 10-day pre-booking push can carry alone.
A13: Campaign 1 (Awareness) creative | B13: Not yet built - to be added once concepts are agreed, likely drawing on Lifestyle Aspiration and Segment Fit territories.
